syn_data_csv/__init__.py
syn_data_csv/constants.py
syn_data_csv/generate_data.py
syn_data_csv/generate_text_prompt.py
syn_data_csv/llm_providers.py
syn_data_csv/llm_setup.py
syn_data_csv/main.py
syn_data_csv/output.py
syn_data_csv/validate_files.py
syn_data_csv/adapters/__init__.py
syn_data_csv/adapters/base.py
syn_data_csv/adapters/groq_adapter.py
syn_data_csv/adapters/hf_adapter.py
syn_data_csv-0.2.2.dist-info/licenses/LICENSE.txt
syn_data_csv-0.2.2.dist-info/METADATA
syn_data_csv-0.2.2.dist-info/WHEEL
syn_data_csv-0.2.2.dist-info/entry_points.txt
syn_data_csv-0.2.2.dist-info/top_level.txt
syn_data_csv-0.2.2.dist-info/RECORD
