Metadata-Version: 2.4
Name: syn_data_csv
Version: 0.2.2
Summary: Synthetic data generation using LLMs
Author-email: Shyam Kota <shyamsundar.kota@infoservices.com>
Maintainer-email: Shyam Kota <shyamsundar.kota@infoservices.com>
License: MIT License
Project-URL: Homepage, https://github.com/Shyamkotainfo/Syn_data_gen/tree/shyam/syn_data_csv
Project-URL: Documentation, https://github.com/Shyamkotainfo/Syn_data_gen/blob/shyam/syn_data_csv/README.md
Requires-Python: >=3.10
License-File: LICENSE.txt
Requires-Dist: groq>=0.25.0
Requires-Dist: pandas>=2.2.3
Requires-Dist: python-dotenv>=1.1.0
Requires-Dist: pyyaml>=6.0.2
Requires-Dist: requests>=2.32.4
Requires-Dist: tqdm>=4.66.4
Requires-Dist: huggingface_hub>=0.23.0
Provides-Extra: dev
Requires-Dist: twine; extra == "dev"
Requires-Dist: build; extra == "dev"
Dynamic: license-file
